alu.v
/* Module:       alu.v
 * Project:      Automated RTL-to-Synthesis & Timing Flow
 * Description: 8-bit Arithmetic Logic Unit (ALU)
 */

module alu (
    input        clk,    // System Clock (Synchronous Design)
    input        rst_n,  // Active Low Asynchronous Reset
    input        en,     // Clock Enable (Gated Clock logic support)
    input  [7:0] a,      // Operand A
    input  [7:0] b,      // Operand B
    input  [3:0] op,     // Operation Code (16 possible ops)
    output reg [7:0] out,   // 8-bit Data Output
    output reg [3:0] flags  // Status Flags: {Negative, Zero, Overflow, Carry}
);

    // 9-bit register to capture Carry-out bit during arithmetic
    reg [8:0] res_temp;

    always @(posedge clk or negedge rst_n) begin
        if (!rst_n) begin
            // Reset State: Clear all outputs
            out   <= 8'b0;
            flags <= 4'b0;
        end else if (en) begin
            // --- 1. EXECUTE OPERATION ---
            case(op)
                // Arithmetic
                4'b0000: res_temp = a + b;       // ADD
                4'b0001: res_temp = a - b;       // SUB
                4'b0010: res_temp = a * b;       // MUL (Lower 8 bits)

                // Bitwise Logic
                4'b0011: res_temp = {1'b0, a & b}; // AND
                4'b0100: res_temp = {1'b0, a | b}; // OR
                4'b0101: res_temp = {1'b0, a ^ b}; // XOR
                4'b0110: res_temp = {1'b0, ~a};    // NOT (Invert)

                // Shifting
                4'b0111: res_temp = {1'b0, a << 1}; // Shift Left
                4'b1000: res_temp = {1'b0, a >> 1}; // Shift Right

                // Comparisons (Output 1 if True)
                4'b1001: res_temp = (a == b) ? 9'd1 : 9'd0; // SEQ (Equal)
                4'b1010: res_temp = (a < b)  ? 9'd1 : 9'd0; // SLT (Less Than)

                default: res_temp = 9'b0;
            endcase

            // --- 2. UPDATE OUTPUTS ---
            out <= res_temp[7:0];

            // --- 3. GENERATE STATUS FLAGS ---
            // Zero (Z): True if result is exactly 0
            flags[2] <= (res_temp[7:0] == 8'b0);
            
            // Negative (N): True if MSB (Sign Bit) is 1
            flags[3] <= res_temp[7];

            // Carry (C): True if 9th bit is 1 (Unsigned Overflow)
            flags[0] <= res_temp[8];

            // Overflow (V): Signed Arithmetic Overflow Check
            if (op == 4'b0000)      // ADD
                flags[1] <= ~(a[7] ^ b[7]) & (a[7] ^ res_temp[7]);
            else if (op == 4'b0001) // SUB
                flags[1] <= (a[7] ^ b[7]) & (a[7] ^ res_temp[7]);
            else
                flags[1] <= 1'b0;
        end
    end
endmodule

tb.v
/* Module:       tb.v
 * Description:  Comprehensive Self-Checking Testbench
 * Features:     - Directed Corner Case Testing
 * - Randomized Testing for ALL ALU Operations (Arithmetic, Logic, Shift, Compare)
 * - Automated Golden Model Verification
 */

module tb;
    // Signals
    reg        clk, rst_n, en;
    reg  [7:0] a, b;
    reg  [3:0] op;
    wire [7:0] out;
    wire [3:0] flags;

    // Test Variables
    integer errors = 0;
    integer i;

    // Instantiate Unit Under Test (UUT)
    alu uut (
        .clk(clk), .rst_n(rst_n), .en(en), 
        .a(a), .b(b), .op(op), 
        .out(out), .flags(flags)
    );

    // Clock Generation: 100MHz (Period = 10ns)
    always #5 clk = ~clk;

    // --- HELPER TASK: CHECK RESULTS ---
    // Calculates the expected value and compares it to the ALU output
    task check_result;
        input [7:0] expected;
        input [23:0] op_name; // Operation name for debug (e.g., "ADD")
        begin
            if (out !== expected) begin
                $display("❌ FAIL: %s | Inputs: A=%d, B=%d | Exp: %d vs Got: %d", 
                         op_name, a, b, expected, out);
                errors = errors + 1;
            end
        end
    endtask

    initial begin
        // Waveform Dump
        $dumpfile("alu.vcd"); 
        $dumpvars(0, tb);

        // Initialize
        clk = 0; rst_n = 0; en = 0; a = 0; b = 0; op = 0;
        
        // Reset Sequence
        #10 rst_n = 1; #10 en = 1;

        $display("\n=== 1. DIRECTED TESTS (Corner Cases) ===");
        
        // Test ADD
        a = 10; b = 20; op = 4'b0000; @(posedge clk); #1;
        check_result(30, "ADD");

        // Test CARRY Flag (255 + 1)
        a = 255; b = 1; op = 4'b0000; @(posedge clk); #1;
        if (flags[0] !== 1) begin 
            $display("❌ FAIL: CARRY Flag not set for 255+1"); errors++; 
        end else begin
            $display("✅ PASS: CARRY Flag detected correctly");
        end

        $display("\n=== 2. RANDOMIZED STRESS TEST (ALL OPS) ===");
        
        // Loop 200 times testing ALL 11 modes of the ALU
        for (i = 0; i < 200; i = i + 1) begin
            a = $random; 
            b = $random; 
            op = $random % 11; // Limit opcode to valid range (0-10)
            
            @(posedge clk); #1;
            
            // The Golden Model: Predicts what the hardware SHOULD do
            case(op)
                // Arithmetic
                4'b0000: check_result(a + b, "ADD");
                4'b0001: check_result(a - b, "SUB");
                4'b0010: check_result(a * b, "MUL");

                // Bitwise Logic
                4'b0011: check_result(a & b, "AND");
                4'b0100: check_result(a | b, "OR ");
                4'b0101: check_result(a ^ b, "XOR");
                4'b0110: check_result(~a,    "NOT");

                // Shift
                4'b0111: check_result(a << 1, "SHL");
                4'b1000: check_result(a >> 1, "SHR");

                // Compare (Condition ? 1 : 0)
                4'b1001: check_result((a == b) ? 8'd1 : 8'd0, "SEQ");
                4'b1010: check_result((a < b)  ? 8'd1 : 8'd0, "SLT");
            endcase
        end
        $display("✅ Completed 200 Random Vectors across ALL modes");

        // Summary
        $display("--------------------------------");
        if (errors == 0) $display("🎉 SUCCESS: ALL TESTS PASSED");
        else $display("❌ FAILURE: %d Errors Found", errors);
        $display("--------------------------------");
        
        $finish;
    end
endmodule

alu.vcd
$date
	Sat Feb 21 22:37:22 2026
$end
$version
	Icarus Verilog
$end
$timescale
	1s
$end
$scope module tb $end
$var wire 8 ! out [7:0] $end
$var wire 4 " flags [3:0] $end
$var reg 8 # a [7:0] $end
$var reg 8 $ b [7:0] $end
$var reg 1 % clk $end
$var reg 1 & en $end
$var reg 4 ' op [3:0] $end
$var reg 1 ( rst_n $end
$var integer 32 ) errors [31:0] $end
$var integer 32 * i [31:0] $end
$scope module uut $end
$var wire 8 + a [7:0] $end
$var wire 8 , b [7:0] $end
$var wire 1 % clk $end
$var wire 1 & en $end
$var wire 4 - op [3:0] $end
$var wire 1 ( rst_n $end
$var reg 4 . flags [3:0] $end
$var reg 8 / out [7:0] $end
$var reg 9 0 res_temp [8:0] $end
$upscope $end
$scope task check_result $end
$var reg 8 1 expected [7:0] $end
$var reg 24 2 op_name [23:0] $end
$upscope $end
$upscope $end
$enddefinitions $end
$comment Show the parameter values. $end
$dumpall
$end
#0
$dumpvars
bx 2
bx 1
bx 0
b0 /
b0 .
b0 -
b0 ,
b0 +
bx *
b0 )
0(
b0 '
0&
0%
b0 $
b0 #
b0 "
b0 !
$end
#5
1%
#10
0%
1(
#15
1%
#20
0%
b10100 $
b10100 ,
b1010 #
b1010 +
1&
#25
b11110 !
b11110 /
b11110 0
1%
#26
b1 $
b1 ,
b11111111 #
b11111111 +
b10000010100010001000100 2
b11110 1
#30
0%
#35
b101 "
b101 .
b0 !
b0 /
b100000000 0
1%
#36
b1110 '
b1110 -
b10000001 $
b10000001 ,
b100100 #
b100100 +
b0 *
#40
0%
#45
b100 "
b100 .
b0 0
1%
#46
b1001 '
b1001 -
b1101 $
b1101 ,
b1100011 #
b1100011 +
b1 *
#50
0%
#55
1%
#56
b10010 $
b10010 ,
b1100101 #
b1100101 +
b10 *
b10100110100010101010001 2
b0 1
#60
0%
#65
1%
#66
b101 '
b101 -
b1110110 $
b1110110 ,
b1101 #
b1101 +
b11 *
#70
0%
#75
b0 "
b0 .
b1111011 !
b1111011 /
b1111011 0
1%
#76
b110 '
b110 -
b10001100 $
b10001100 ,
b11101101 #
b11101101 +
b100 *
b10110000100111101010010 2
b1111011 1
#80
0%
#85
b10010 !
b10010 /
b10010 0
1%
#86
b1101 '
b1101 -
b11000101 $
b11000101 ,
b11000110 #
b11000110 +
b101 *
b10011100100111101010100 2
b10010 1
#90
0%
#95
b100 "
b100 .
b0 !
b0 /
b0 0
1%
#96
b1110 '
b1110 -
b1110111 $
b1110111 ,
b11100101 #
b11100101 +
b110 *
#100
0%
#105
1%
#106
b11110010 $
b11110010 ,
b10001111 #
b10001111 +
b111 *
#110
0%
#115
1%
#116
b10 '
b10 -
b11000101 $
b11000101 ,
b11101000 #
b11101000 +
b1000 *
#120
0%
#125
b1000 "
b1000 .
b10001000 !
b10001000 /
b10001000 0
1%
#126
b1101 '
b1101 -
b101101 $
b101101 ,
b10111101 #
b10111101 +
b1001 *
b10011010101010101001100 2
b10001000 1
#130
0%
#135
b100 "
b100 .
b0 !
b0 /
b0 0
1%
#136
b110 '
b110 -
b1010 $
b1010 ,
b1100011 #
b1100011 +
b1010 *
#140
0%
#145
b1000 "
b1000 .
b10011100 !
b10011100 /
b10011100 0
1%
#146
b10101010 $
b10101010 ,
b100000 #
b100000 +
b1011 *
b10011100100111101010100 2
b10011100 1
#150
0%
#155
b11011111 !
b11011111 /
b11011111 0
1%
#156
b1110 '
b1110 -
b10011 $
b10011 ,
b10010110 #
b10010110 +
b1100 *
b11011111 1
#160
0%
#165
b100 "
b100 .
b0 !
b0 /
b0 0
1%
#166
b1100 '
b1100 -
b1101011 $
b1101011 ,
b1010011 #
b1010011 +
b1101 *
#170
0%
#175
1%
#176
b10 '
b10 -
b10101110 $
b10101110 ,
b10 #
b10 +
b1110 *
#180
0%
#185
b1 "
b1 .
b1011100 !
b1011100 /
b101011100 0
1%
#186
b1 '
b1 -
b100011 $
b100011 ,
b11001111 #
b11001111 +
b1111 *
b10011010101010101001100 2
b1011100 1
#190
0%
#195
b1000 "
b1000 .
b10101100 !
b10101100 /
b10101100 0
1%
#196
b111 '
b111 -
b111100 $
b111100 ,
b11001010 #
b11001010 +
b10000 *
b10100110101010101000010 2
b10101100 1
#200
0%
#205
b10010100 !
b10010100 /
b10010100 0
1%
#206
b110 '
b110 -
b1000001 $
b1000001 ,
b10001010 #
b10001010 +
b10001 *
b10100110100100001001100 2
b10010100 1
#210
0%
#215
b0 "
b0 .
b1110101 !
b1110101 /
b1110101 0
1%
#216
b11 '
b11 -
b10001001 $
b10001001 ,
b1111000 #
b1111000 +
b10010 *
b10011100100111101010100 2
b1110101 1
#220
0%
#225
b1000 !
b1000 /
b1000 0
1%
#226
b1000 '
b1000 -
b11000110 $
b11000110 ,
b10110110 #
b10110110 +
b10011 *
b10000010100111001000100 2
b1000 1
#230
0%
#235
b1011011 !
b1011011 /
b1011011 0
1%
#236
b0 '
b0 -
b101010 $
b101010 ,
b10111100 #
b10111100 +
b10100 *
b10100110100100001010010 2
b1011011 1
#240
0%
#245
b1000 "
b1000 .
b11100110 !
b11100110 /
b11100110 0
1%
#246
b1 '
b1 -
b10000101 $
b10000101 ,
b1110001 #
b1110001 +
b10101 *
b10000010100010001000100 2
b11100110 1
#250
0%
#255
b1011 "
b1011 .
b11101100 !
b11101100 /
b111101100 0
1%
#256
b111 '
b111 -
b111010 $
b111010 ,
b111011 #
b111011 +
b10110 *
b10100110101010101000010 2
b11101100 1
#260
0%
#265
b0 "
b0 .
b1110110 !
b1110110 /
b1110110 0
1%
#266
b1010 '
b1010 -
b11110001 $
b11110001 ,
b10101 #
b10101 +
b10111 *
b10100110100100001001100 2
b1110110 1
#270
0%
#275
b1 !
b1 /
b1 0
1%
#276
b11 '
b11 -
b1001100 $
b1001100 ,
b1100010 #
b1100010 +
b11000 *
b10100110100110001010100 2
b1 1
#280
0%
#285
b1000000 !
b1000000 /
b1000000 0
1%
#286
b1101 '
b1101 -
b11111000 $
b11111000 ,
b10001111 #
b10001111 +
b11001 *
b10000010100111001000100 2
b1000000 1
#290
0%
#295
b100 "
b100 .
b0 !
b0 /
b0 0
1%
#296
b0 '
b0 -
b1011100 $
b1011100 ,
b10011111 #
b10011111 +
b11010 *
#300
0%
#305
b1000 "
b1000 .
b11111011 !
b11111011 /
b11111011 0
1%
#306
b1011 '
b1011 -
b1001001 $
b1001001 ,
b10001001 #
b10001001 +
b11011 *
b10000010100010001000100 2
b11111011 1
#310
0%
#315
b100 "
b100 .
b0 !
b0 /
b0 0
1%
#316
b110 '
b110 -
b1010001 $
b1010001 ,
b11010111 #
b11010111 +
b11100 *
#320
0%
#325
b0 "
b0 .
b101000 !
b101000 /
b101000 0
1%
#326
b101 '
b101 -
b11000010 $
b11000010 ,
b1100 #
b1100 +
b11101 *
b10011100100111101010100 2
b101000 1
#330
0%
#335
b1000 "
b1000 .
b11001110 !
b11001110 /
b11001110 0
1%
#336
b11 '
b11 -
b111101 $
b111101 ,
b1110111 #
b1110111 +
b11110 *
b10110000100111101010010 2
b11001110 1
#340
0%
#345
b0 "
b0 .
b110101 !
b110101 /
b110101 0
1%
#346
b101 '
b101 -
b1101101 $
b1101101 ,
b1111110 #
b1111110 +
b11111 *
b10000010100111001000100 2
b110101 1
#350
0%
#355
b10011 !
b10011 /
b10011 0
1%
#356
b11010011 $
b11010011 ,
b11111 #
b11111 +
b100000 *
b10110000100111101010010 2
b10011 1
#360
0%
#365
b1000 "
b1000 .
b11001100 !
b11001100 /
b11001100 0
1%
#366
b10 '
b10 -
b1011011 $
b1011011 ,
b1111000 #
b1111000 +
b100001 *
b11001100 1
#370
0%
#375
b10101000 !
b10101000 /
b10101000 0
1%
#376
b101010 $
b101010 ,
b111111 #
b111111 +
b100010 *
b10011010101010101001100 2
b10101000 1
#380
0%
#385
b0 "
b0 .
b1010110 !
b1010110 /
b1010110 0
1%
#386
b1111 '
b1111 -
b10001110 $
b10001110 ,
b10000110 #
b10000110 +
b100011 *
b1010110 1
#390
0%
#395
b100 "
b100 .
b0 !
b0 /
b0 0
1%
#396
b100 '
b100 -
b100110 $
b100110 ,
b11111010 #
b11111010 +
b100100 *
#400
0%
#405
b1000 "
b1000 .
b11111110 !
b11111110 /
b11111110 0
1%
#406
b111 '
b111 -
b101111 $
b101111 ,
b10100011 #
b10100011 +
b100101 *
b10011110101001000100000 2
b11111110 1
#410
0%
#415
b0 "
b0 .
b1000110 !
b1000110 /
b1000110 0
1%
#416
b11 '
b11 -
b1000100 $
b1000100 ,
b1011111 #
b1011111 +
b100110 *
b10100110100100001001100 2
b1000110 1
#420
0%
#425
b1000100 !
b1000100 /
b1000100 0
1%
#426
b1 '
b1 -
b11100110 $
b11100110 ,
b11001011 #
b11001011 +
b100111 *
b10000010100111001000100 2
b1000100 1
#430
0%
#435
b1001 "
b1001 .
b11100101 !
b11100101 /
b111100101 0
1%
#436
b1011 '
b1011 -
b11101101 $
b11101101 ,
b101001 #
b101001 +
b101000 *
b10100110101010101000010 2
b11100101 1
#440
0%
#445
b100 "
b100 .
b0 !
b0 /
b0 0
1%
#446
b1001 '
b1001 -
b10110101 $
b10110101 ,
b1100101 #
b1100101 +
b101001 *
#450
0%
#455
1%
#456
b111 '
b111 -
b1000100 $
b1000100 ,
b1111001 #
b1111001 +
b101010 *
b10100110100010101010001 2
b0 1
#460
0%
#465
b1000 "
b1000 .
b11110010 !
b11110010 /
b11110010 0
1%
#466
b1000 '
b1000 -
b10101011 $
b10101011 ,
b101010 #
b101010 +
b101011 *
b10100110100100001001100 2
b11110010 1
#470
0%
#475
b0 "
b0 .
b10101 !
b10101 /
b10101 0
1%
#476
b1100 '
b1100 -
b10011010 $
b10011010 ,
b11011100 #
b11011100 +
b101100 *
b10100110100100001010010 2
b10101 1
#480
0%
#485
b100 "
b100 .
b0 !
b0 /
b0 0
1%
#486
b100 '
b100 -
b1010110 $
b1010110 ,
b11000011 #
b11000011 +
b101101 *
#490
0%
#495
b1000 "
b1000 .
b11010111 !
b11010111 /
b11010111 0
1%
#496
b10 '
b10 -
b1010 $
b1010 ,
b1100111 #
b1100111 +
b101110 *
b10011110101001000100000 2
b11010111 1
#500
0%
#505
b0 "
b0 .
b110 !
b110 /
b110 0
1%
#506
b0 '
b0 -
b1111001 $
b1111001 ,
b111000 #
b111000 +
b101111 *
b10011010101010101001100 2
b110 1
#510
0%
#515
b1010 "
b1010 .
b10110001 !
b10110001 /
b10110001 0
1%
#516
b1100 '
b1100 -
b10010011 $
b10010011 ,
b10010100 #
b10010100 +
b110000 *
b10000010100010001000100 2
b10110001 1
#520
0%
#525
b100 "
b100 .
b0 !
b0 /
b0 0
1%
#526
b1110 '
b1110 -
b11011011 $
b11011011 ,
b1011001 #
b1011001 +
b110001 *
#530
0%
#535
1%
#536
b1010 '
b1010 -
b1101101 $
b1101101 ,
b11011001 #
b11011001 +
b110010 *
#540
0%
#545
1%
#546
b11 '
b11 -
b10110110 $
b10110110 ,
b11001010 #
b11001010 +
b110011 *
b10100110100110001010100 2
b0 1
#550
0%
#555
b1000 "
b1000 .
b10000010 !
b10000010 /
b10000010 0
1%
#556
b111 '
b111 -
b100 $
b100 ,
b1000110 #
b1000110 +
b110100 *
b10000010100111001000100 2
b10000010 1
#560
0%
#565
b10001100 !
b10001100 /
b10001100 0
1%
#566
b110 '
b110 -
b10110100 $
b10110100 ,
b1101001 #
b1101001 +
b110101 *
b10100110100100001001100 2
b10001100 1
#570
0%
#575
b10010110 !
b10010110 /
b10010110 0
1%
#576
b111 '
b111 -
b101101 $
b101101 ,
b101000 #
b101000 +
b110110 *
b10011100100111101010100 2
b10010110 1
#580
0%
#585
b0 "
b0 .
b1010000 !
b1010000 /
b1010000 0
1%
#586
b1010 '
b1010 -
b1000 $
b1000 ,
b101110 #
b101110 +
b110111 *
b10100110100100001001100 2
b1010000 1
#590
0%
#595
b100 "
b100 .
b0 !
b0 /
b0 0
1%
#596
b0 '
b0 -
b101001 $
b101001 ,
b11111101 #
b11111101 +
b111000 *
b10100110100110001010100 2
b0 1
#600
0%
#605
b1 "
b1 .
b100110 !
b100110 /
b100100110 0
1%
#606
b1101 '
b1101 -
b11011010 $
b11011010 ,
b10000110 #
b10000110 +
b111001 *
b10000010100010001000100 2
b100110 1
#610
0%
#615
b100 "
b100 .
b0 !
b0 /
b0 0
1%
#616
b1110000 $
b1110000 ,
b1100110 #
b1100110 +
b111010 *
#620
0%
#625
1%
#626
b111 '
b111 -
b1011110 $
b1011110 ,
b10111010 #
b10111010 +
b111011 *
#630
0%
#635
b0 "
b0 .
b1110100 !
b1110100 /
b1110100 0
1%
#636
b1110 '
b1110 -
b11010 $
b11010 ,
b11010101 #
b11010101 +
b111100 *
b10100110100100001001100 2
b1110100 1
#640
0%
#645
b100 "
b100 .
b0 !
b0 /
b0 0
1%
#646
b1000 '
b1000 -
b10010110 $
b10010110 ,
b110111 #
b110111 +
b111101 *
#650
0%
#655
b0 "
b0 .
b11011 !
b11011 /
b11011 0
1%
#656
b101 '
b101 -
b10110110 $
b10110110 ,
b100110 #
b100110 +
b111110 *
b10100110100100001010010 2
b11011 1
#660
0%
#665
b1000 "
b1000 .
b10010000 !
b10010000 /
b10010000 0
1%
#666
b10 '
b10 -
b10000110 $
b10000110 ,
b11011100 #
b11011100 +
b111111 *
b10110000100111101010010 2
b10010000 1
#670
0%
#675
b1 "
b1 .
b101000 !
b101000 /
b100101000 0
1%
#676
b1100 '
b1100 -
b11011011 $
b11011011 ,
b1111110 #
b1111110 +
b1000000 *
b10011010101010101001100 2
b101000 1
#680
0%
#685
b100 "
b100 .
b0 !
b0 /
b0 0
1%
#686
b111 '
b111 -
b11111010 $
b11111010 ,
b1111001 #
b1111001 +
b1000001 *
#690
0%
#695
b1000 "
b1000 .
b11110010 !
b11110010 /
b11110010 0
1%
#696
b110 '
b110 -
b10100001 $
b10100001 ,
b10111 #
b10111 +
b1000010 *
b10100110100100001001100 2
b11110010 1
#700
0%
#705
b11101000 !
b11101000 /
b11101000 0
1%
#706
b1110 '
b1110 -
b11110101 $
b11110101 ,
b1010000 #
b1010000 +
b1000011 *
b10011100100111101010100 2
b11101000 1
#710
0%
#715
b100 "
b100 .
b0 !
b0 /
b0 0
1%
#716
b1000 '
b1000 -
b11000001 $
b11000001 ,
b101001 #
b101001 +
b1000100 *
#720
0%
#725
b0 "
b0 .
b10100 !
b10100 /
b10100 0
1%
#726
b1101 '
b1101 -
b1001011 $
b1001011 ,
b10011000 #
b10011000 +
b1000101 *
b10100110100100001010010 2
b10100 1
#730
0%
#735
b100 "
b100 .
b0 !
b0 /
b0 0
1%
#736
b1001 '
b1001 -
b10001010 $
b10001010 ,
b11101100 #
b11101100 +
b1000110 *
#740
0%
#745
1%
#746
b1000 '
b1000 -
b10101001 $
b10101001 ,
b10101000 #
b10101000 +
b1000111 *
b10100110100010101010001 2
b0 1
#750
0%
#755
b0 "
b0 .
b1010100 !
b1010100 /
b1010100 0
1%
#756
b1100 '
b1100 -
b11100110 $
b11100110 ,
b1110 #
b1110 +
b1001000 *
b10100110100100001010010 2
b1010100 1
#760
0%
#765
b100 "
b100 .
b0 !
b0 /
b0 0
1%
#766
b110 '
b110 -
b101010 $
b101010 ,
b101010 #
b101010 +
b1001001 *
#770
0%
#775
b1000 "
b1000 .
b11010101 !
b11010101 /
b11010101 0
1%
#776
b1000 '
b1000 -
b111000 $
b111000 ,
b10011110 #
b10011110 +
b1001010 *
b10011100100111101010100 2
b11010101 1
#780
0%
#785
b0 "
b0 .
b1001111 !
b1001111 /
b1001111 0
1%
#786
b10 '
b10 -
b11001010 $
b11001010 ,
b11001000 #
b11001000 +
b1001011 *
b10100110100100001010010 2
b1001111 1
#790
0%
#795
b1001 "
b1001 .
b11010000 !
b11010000 /
b111010000 0
1%
#796
b11000111 $
b11000111 ,
b1101011 #
b1101011 +
b1001100 *
b10011010101010101001100 2
b11010000 1
#800
0%
#805
b1 "
b1 .
b101101 !
b101101 /
b100101101 0
1%
#806
b111 '
b111 -
b11000100 $
b11000100 ,
b10111010 #
b10111010 +
b1001101 *
b101101 1
#810
0%
#815
b0 "
b0 .
b1110100 !
b1110100 /
b1110100 0
1%
#816
b11 '
b11 -
b10110100 $
b10110100 ,
b10010010 #
b10010010 +
b1001110 *
b10100110100100001001100 2
b1110100 1
#820
0%
#825
b1000 "
b1000 .
b10010000 !
b10010000 /
b10010000 0
1%
#826
b110 '
b110 -
b11111010 $
b11111010 ,
b10000110 #
b10000110 +
b1001111 *
b10000010100111001000100 2
b10010000 1
#830
0%
#835
b0 "
b0 .
b1111001 !
b1111001 /
b1111001 0
1%
#836
b10111101 $
b10111101 ,
b110010 #
b110010 +
b1010000 *
b10011100100111101010100 2
b1111001 1
#840
0%
#845
b1000 "
b1000 .
b11001101 !
b11001101 /
b11001101 0
1%
#846
b0 '
b0 -
b11001010 $
b11001010 ,
b11100100 #
b11100100 +
b1010001 *
b11001101 1
#850
0%
#855
b1001 "
b1001 .
b10101110 !
b10101110 /
b110101110 0
1%
#856
b110 '
b110 -
b10001110 $
b10001110 ,
b10100001 #
b10100001 +
b1010010 *
b10000010100010001000100 2
b10101110 1
#860
0%
#865
b0 "
b0 .
b1011110 !
b1011110 /
b1011110 0
1%
#866
b0 '
b0 -
b11101111 $
b11101111 ,
b1011 #
b1011 +
b1010011 *
b10011100100111101010100 2
b1011110 1
#870
0%
#875
b1000 "
b1000 .
b11111010 !
b11111010 /
b11111010 0
1%
#876
b1001 '
b1001 -
b1110101 $
b1110101 ,
b110110 #
b110110 +
b1010100 *
b10000010100010001000100 2
b11111010 1
#880
0%
#885
b100 "
b100 .
b0 !
b0 /
b0 0
1%
#886
b1110 '
b1110 -
b10001000 $
b10001000 ,
b1101011 #
b1101011 +
b1010101 *
b10100110100010101010001 2
b0 1
#890
0%
#895
1%
#896
b10 '
b10 -
b10010010 $
b10010010 ,
b10011011 #
b10011011 +
b1010110 *
#900
0%
#905
b0 "
b0 .
b1100110 !
b1100110 /
b1100110 0
1%
#906
b1010 '
b1010 -
b1001011 $
b1001011 ,
b101101 #
b101101 +
b1010111 *
b10011010101010101001100 2
b1100110 1
#910
0%
#915
b1 !
b1 /
b1 0
1%
#916
b1 '
b1 -
b1101 $
b1101 ,
b11110 #
b11110 +
b1011000 *
b10100110100110001010100 2
b1 1
#920
0%
#925
b10001 !
b10001 /
b10001 0
1%
#926
b1100 '
b1100 -
b11010001 $
b11010001 ,
b11000 #
b11000 +
b1011001 *
b10100110101010101000010 2
b10001 1
#930
0%
#935
b100 "
b100 .
b0 !
b0 /
b0 0
1%
#936
b11 '
b11 -
b111011 $
b111011 ,
b1000001 #
b1000001 +
b1011010 *
#940
0%
#945
b0 "
b0 .
b1 !
b1 /
b1 0
1%
#946
b1011 '
b1011 -
b1010110 $
b1010110 ,
b1010011 #
b1010011 +
b1011011 *
b10000010100111001000100 2
b1 1
#950
0%
#955
b100 "
b100 .
b0 !
b0 /
b0 0
1%
#956
b1010 '
b1010 -
b100 $
b100 ,
b11100010 #
b11100010 +
b1011100 *
#960
0%
#965
1%
#966
b1001 '
b1001 -
b10010 $
b10010 ,
b11011000 #
b11011000 +
b1011101 *
b10100110100110001010100 2
b0 1
#970
0%
#975
1%
#976
b0 '
b0 -
b11100101 $
b11100101 ,
b111001 #
b111001 +
b1011110 *
b10100110100010101010001 2
#980
0%
#985
b1 "
b1 .
b11110 !
b11110 /
b100011110 0
1%
#986
b10000001 $
b10000001 ,
b101011 #
b101011 +
b1011111 *
b10000010100010001000100 2
b11110 1
#990
0%
#995
b1000 "
b1000 .
b10101100 !
b10101100 /
b10101100 0
1%
#996
b10100001 $
b10100001 ,
b100111 #
b100111 +
b1100000 *
b10101100 1
#1000
0%
#1005
b11001000 !
b11001000 /
b11001000 0
1%
#1006
b1101 '
b1101 -
b1011000 $
b1011000 ,
b100 #
b100 +
b1100001 *
b11001000 1
#1010
0%
#1015
b100 "
b100 .
b0 !
b0 /
b0 0
1%
#1016
b1111 '
b1111 -
b10010 $
b10010 ,
b10100 #
b10100 +
b1100010 *
#1020
0%
#1025
1%
#1026
b1000 '
b1000 -
b1010101 $
b1010101 ,
b10110001 #
b10110001 +
b1100011 *
#1030
0%
#1035
b0 "
b0 .
b1011000 !
b1011000 /
b1011000 0
1%
#1036
b1010 '
b1010 -
b11110101 $
b11110101 ,
b101011 #
b101011 +
b1100100 *
b10100110100100001010010 2
b1011000 1
#1040
0%
#1045
b1 !
b1 /
b1 0
1%
#1046
b1001 '
b1001 -
b10000100 $
b10000100 ,
b100111 #
b100111 +
b1100101 *
b10100110100110001010100 2
b1 1
#1050
0%
#1055
b100 "
b100 .
b0 !
b0 /
b0 0
1%
#1056
b1100 '
b1100 -
b10111001 $
b10111001 ,
b11100111 #
b11100111 +
b1100110 *
b10100110100010101010001 2
b0 1
#1060
0%
#1065
1%
#1066
b0 '
b0 -
b11001001 $
b11001001 ,
b11011011 #
b11011011 +
b1100111 *
#1070
0%
#1075
b1001 "
b1001 .
b10100100 !
b10100100 /
b110100100 0
1%
#1076
b1000 '
b1000 -
b101010 $
b101010 ,
b10100001 #
b10100001 +
b1101000 *
b10000010100010001000100 2
b10100100 1
#1080
0%
#1085
b0 "
b0 .
b1010000 !
b1010000 /
b1010000 0
1%
#1086
b0 '
b0 -
b10000011 $
b10000011 ,
b1000101 #
b1000101 +
b1101001 *
b10100110100100001010010 2
b1010000 1
#1090
0%
#1095
b1000 "
b1000 .
b11001000 !
b11001000 /
b11001000 0
1%
#1096
b1010 '
b1010 -
b11111110 $
b11111110 ,
b1110010 #
b1110010 +
b1101010 *
b10000010100010001000100 2
b11001000 1
#1100
0%
#1105
b0 "
b0 .
b1 !
b1 /
b1 0
1%
#1106
b0 '
b0 -
b10000110 $
b10000110 ,
b1101111 #
b1101111 +
b1101011 *
b10100110100110001010100 2
b1 1
#1110
0%
#1115
b1000 "
b1000 .
b11110101 !
b11110101 /
b11110101 0
1%
#1116
b110 '
b110 -
b1000000 $
b1000000 ,
b111000 #
b111000 +
b1101100 *
b10000010100010001000100 2
b11110101 1
#1120
0%
#1125
b11000111 !
b11000111 /
b11000111 0
1%
#1126
b10 '
b10 -
b11000101 $
b11000101 ,
b11110110 #
b11110110 +
b1101101 *
b10011100100111101010100 2
b11000111 1
#1130
0%
#1135
b1 "
b1 .
b1001110 !
b1001110 /
b101001110 0
1%
#1136
b1010 '
b1010 -
b111001 $
b111001 ,
b1110100 #
b1110100 +
b1101110 *
b10011010101010101001100 2
b1001110 1
#1140
0%
#1145
b100 "
b100 .
b0 !
b0 /
b0 0
1%
#1146
b10 '
b10 -
b101010 $
b101010 ,
b111100 #
b111100 +
b1101111 *
b10100110100110001010100 2
b0 1
#1150
0%
#1155
b1001 "
b1001 .
b11011000 !
b11011000 /
b111011000 0
1%
#1156
b1001 '
b1001 -
b11100001 $
b11100001 ,
b10101 #
b10101 +
b1110000 *
b10011010101010101001100 2
b11011000 1
#1160
0%
#1165
b100 "
b100 .
b0 !
b0 /
b0 0
1%
#1166
b1101 '
b1101 -
b11001001 $
b11001001 ,
b1000011 #
b1000011 +
b1110001 *
b10100110100010101010001 2
b0 1
#1170
0%
#1175
1%
#1176
b110 '
b110 -
b11000001 $
b11000001 ,
b100101 #
b100101 +
b1110010 *
#1180
0%
#1185
b1000 "
b1000 .
b11011010 !
b11011010 /
b11011010 0
1%
#1186
b0 '
b0 -
b111 $
b111 ,
b1011010 #
b1011010 +
b1110011 *
b10011100100111101010100 2
b11011010 1
#1190
0%
#1195
b0 "
b0 .
b1100001 !
b1100001 /
b1100001 0
1%
#1196
b1000 '
b1000 -
b1110001 $
b1110001 ,
b1100 #
b1100 +
b1110100 *
b10000010100010001000100 2
b1100001 1
#1200
0%
#1205
b110 !
b110 /
b110 0
1%
#1206
b1100 '
b1100 -
b11110111 $
b11110111 ,
b10110110 #
b10110110 +
b1110101 *
b10100110100100001010010 2
b110 1
#1210
0%
#1215
b100 "
b100 .
b0 !
b0 /
b0 0
1%
#1216
b111 '
b111 -
b1010101 $
b1010101 ,
b1011100 #
b1011100 +
b1110110 *
#1220
0%
#1225
b1000 "
b1000 .
b10111000 !
b10111000 /
b10111000 0
1%
#1226
b1110010 $
b1110010 ,
b10100000 #
b10100000 +
b1110111 *
b10100110100100001001100 2
b10111000 1
